estruttura/__init__.py
estruttura/_attribute.py
estruttura/_bases.py
estruttura/_dict.py
estruttura/_helpers.py
estruttura/_list.py
estruttura/_relationship.py
estruttura/_set.py
estruttura/_structure.py
estruttura/constants.py
estruttura/exceptions.py
estruttura/py.typed
estruttura/serializers.py
estruttura/examples/__init__.py
estruttura/examples/_class.py
estruttura/examples/_dict.py
estruttura/examples/_list.py
estruttura/examples/_set.py
estruttura-4.0.0.dist-info/LICENSE
estruttura-4.0.0.dist-info/METADATA
estruttura-4.0.0.dist-info/WHEEL
estruttura-4.0.0.dist-info/top_level.txt
estruttura-4.0.0.dist-info/RECORD
