Metadata-Version: 2.1
Name: estruttura
Version: 4.0.0
Summary: Abstract data structures.
Home-page: https://github.com/brunonicko/estruttura
Author: Bruno Nicko
Author-email: brunonicko@gmail.com
Classifier: Intended Audience :: Developers
Classifier: License :: OSI Approved :: MIT License
Classifier: Operating System :: OS Independent
Classifier: Programming Language :: Python :: 2.7
Classifier: Programming Language :: Python :: 3.7
Classifier: Programming Language :: Python :: 3.8
Classifier: Programming Language :: Python :: 3.9
Classifier: Programming Language :: Python :: 3.10
Classifier: Programming Language :: Python :: 3.11
Classifier: Programming Language :: Python :: Implementation :: PyPy
Requires-Python: >= 2.7, != 3.0.*, != 3.1.*, != 3.2.*, != 3.3.*, != 3.4.*, != 3.5.*, != 3.6.*
License-File: LICENSE
Requires-Dist: tippo (<4,>=3.9)
Requires-Dist: basicco (<9,>=8.13)
Requires-Dist: slotted (<5,>=4.3)
Requires-Dist: six
Requires-Dist: pyrsistent (<1,>=0)
